data_analyzer/__init__.py
data_analyzer/app.py
data2stream-0.1.0.dist-info/entry_points.txt
data2stream-0.1.0.dist-info/METADATA
data2stream-0.1.0.dist-info/WHEEL
data2stream-0.1.0.dist-info/RECORD
