Metadata-Version: 2.4
Name: data2stream
Version: 0.1.0
Summary: Streamlit Data Analyzer
License: MIT
Author: python123
Requires-Python: >=3.12,<4.0
Classifier: License :: OSI Approved :: MIT License
Classifier: Programming Language :: Python :: 3
Classifier: Programming Language :: Python :: 3.12
Classifier: Programming Language :: Python :: 3.13
Classifier: Programming Language :: Python :: 3.14
Requires-Dist: matplotlib (>=3.9,<4.0)
Requires-Dist: numpy (>=1.26,<2.0)
Requires-Dist: pandas (>=2.0,<3.0)
Requires-Dist: streamlit (>=1.38.0,<2.0.0)
